canberra/__init__.py
canberra/_canberra.cpython-37m-x86_64-linux-gnu.so
canberra/_canberra.pyi
canberra/constants.py
canberra/convenience.py
py_canberra-0.0.4.dist-info/LICENSE.txt
py_canberra-0.0.4.dist-info/METADATA
py_canberra-0.0.4.dist-info/WHEEL
py_canberra-0.0.4.dist-info/top_level.txt
py_canberra-0.0.4.dist-info/RECORD
