Metadata-Version: 2.1
Name: py-canberra
Version: 0.0.4
Summary: Wrappers for the libcanberra sound-playing interface
Home-page: https://github.com/theY4Kman/py-canberra
Author: Zach "theY4Kman" Kanzler
Author-email: they4kman@gmail.com
License: MIT
Project-URL: Repository, https://github.com/theY4Kman/py-canberra
Project-URL: Documentation, https://py-canberra.readthedocs.io/
Platform: UNKNOWN
Classifier: Development Status :: 3 - Alpha
Classifier: License :: OSI Approved :: MIT License
Classifier: Operating System :: POSIX :: Linux
Classifier: Programming Language :: Python :: 3 :: Only
Classifier: Programming Language :: Python :: 3.6
Classifier: Programming Language :: Python :: 3.7
Classifier: Programming Language :: Python :: 3.8
Classifier: Programming Language :: Python :: Implementation :: CPython
Classifier: Topic :: Multimedia :: Sound/Audio
Requires-Python: ==3.*,>=3.6.0
Provides-Extra: dev
Requires-Dist: cython (==0.*,>=0.29.19) ; extra == 'dev'
